refraction/__init__.py
refraction/app.py
refraction/google.py
refraction/storage.py
refraction/timeUtils.py
refraction-0.1.dist-info/LICENSE.txt
refraction-0.1.dist-info/METADATA
refraction-0.1.dist-info/WHEEL
refraction-0.1.dist-info/top_level.txt
refraction-0.1.dist-info/RECORD
