Metadata-Version: 2.1
Name: refraction
Version: 0.1
Summary: Flask WSGI server for sharing individual rows of spreadsheets with CAS-authenticated users named in those rows.
Home-page: https://cs.wellesley.edu/~pmwh/refraction/docs/refraction
Author: Peter Mawhorter
Author-email: pmawhort@wellesley.edu
License: BSD 3-Clause License
Classifier: Programming Language :: Python :: 3 :: Only
Classifier: Development Status :: 3 - Alpha
Classifier: Intended Audience :: Developers
Classifier: Intended Audience :: Education
Classifier: License :: OSI Approved :: BSD License
Classifier: Operating System :: OS Independent
Classifier: Natural Language :: English
Classifier: Topic :: Education
Classifier: Topic :: Office/Business
Classifier: Topic :: Other/Nonlisted Topic
Classifier: Topic :: Internet :: WWW/HTTP :: WSGI :: Application
Requires-Python: >=2.7
License-File: LICENSE.txt
Provides-Extra: google
Requires-Dist: google ; extra == 'google'
Requires-Dist: googleapiclient ; extra == 'google'
Provides-Extra: https_debug
Requires-Dist: openssl ; extra == 'https_debug'
Provides-Extra: security
Requires-Dist: flask-talisman ; extra == 'security'
Requires-Dist: flask-seasurf ; extra == 'security'
Provides-Extra: test
Requires-Dist: pytest ; extra == 'test'
